classifier_checker/__init__.py
classifier_checker/__main__.py
classifier_checker/argparser.py
classifier_checker/classifier_checks.py
classifier_checker/logger.py
classifier_checker/py.typed
classifier_checker/utils.py
classifier_checker/version.py
classifier_checker-0.1.2.dist-info/LICENSE
classifier_checker-0.1.2.dist-info/METADATA
classifier_checker-0.1.2.dist-info/WHEEL
classifier_checker-0.1.2.dist-info/entry_points.txt
classifier_checker-0.1.2.dist-info/top_level.txt
classifier_checker-0.1.2.dist-info/RECORD
