Metadata-Version: 2.1
Name: classifier-checker
Version: 0.1.2
Summary: Classifier-checker validates configured classifiers for you!
Home-page: https://github.com/ThomasTNO/classifier-checker
Download-URL: https://pypi.org/project/classifier-checker/#files
Author: Thomas Rooijakkers
Author-email: thomas.rooijakkers@tno.nl
Maintainer: Thomas Rooijakkers
Maintainer-email: thomas.rooijakkers@tno.nl
License: MIT License
Project-URL: Source Code, https://github.com/ThomasTNO/classifier-checker
Keywords: classifier,checker,check,validate,validation
Platform: any
Classifier: License :: OSI Approved :: MIT License
Classifier: Programming Language :: Python :: 3
Classifier: Operating System :: OS Independent
Classifier: Intended Audience :: Developers
Classifier: Intended Audience :: System Administrators
Classifier: Typing :: Typed
License-File: LICENSE
Requires-Dist: trove-classifiers
